sphinx_dropdown_toggle/__init__.py
sphinx_dropdown_toggle/_version.py
sphinx_dropdown_toggle/static/dropdown_toggle.js
sphinx_dropdown_toggle/translations/README.md
sphinx_dropdown_toggle/translations/_convert.py
sphinx_dropdown_toggle/translations/jsons/Close.json
sphinx_dropdown_toggle/translations/jsons/Mixed.json
sphinx_dropdown_toggle/translations/jsons/Open.json
sphinx_dropdown_toggle/translations/locales/ar/LC_MESSAGES/dropdowntoggle.mo
sphinx_dropdown_toggle/translations/locales/ar/LC_MESSAGES/dropdowntoggle.po
sphinx_dropdown_toggle/translations/locales/bn/LC_MESSAGES/dropdowntoggle.mo
sphinx_dropdown_toggle/translations/locales/bn/LC_MESSAGES/dropdowntoggle.po
sphinx_dropdown_toggle/translations/locales/cs/LC_MESSAGES/dropdowntoggle.mo
sphinx_dropdown_toggle/translations/locales/cs/LC_MESSAGES/dropdowntoggle.po
sphinx_dropdown_toggle/translations/locales/de/LC_MESSAGES/dropdowntoggle.mo
sphinx_dropdown_toggle/translations/locales/de/LC_MESSAGES/dropdowntoggle.po
sphinx_dropdown_toggle/translations/locales/el/LC_MESSAGES/dropdowntoggle.mo
sphinx_dropdown_toggle/translations/locales/el/LC_MESSAGES/dropdowntoggle.po
sphinx_dropdown_toggle/translations/locales/es/LC_MESSAGES/dropdowntoggle.mo
sphinx_dropdown_toggle/translations/locales/es/LC_MESSAGES/dropdowntoggle.po
sphinx_dropdown_toggle/translations/locales/fa/LC_MESSAGES/dropdowntoggle.mo
sphinx_dropdown_toggle/translations/locales/fa/LC_MESSAGES/dropdowntoggle.po
sphinx_dropdown_toggle/translations/locales/fr/LC_MESSAGES/dropdowntoggle.mo
sphinx_dropdown_toggle/translations/locales/fr/LC_MESSAGES/dropdowntoggle.po
sphinx_dropdown_toggle/translations/locales/he/LC_MESSAGES/dropdowntoggle.mo
sphinx_dropdown_toggle/translations/locales/he/LC_MESSAGES/dropdowntoggle.po
sphinx_dropdown_toggle/translations/locales/hi/LC_MESSAGES/dropdowntoggle.mo
sphinx_dropdown_toggle/translations/locales/hi/LC_MESSAGES/dropdowntoggle.po
sphinx_dropdown_toggle/translations/locales/hu/LC_MESSAGES/dropdowntoggle.mo
sphinx_dropdown_toggle-1.3.3.dist-info/METADATA
sphinx_dropdown_toggle-1.3.3.dist-info/WHEEL
sphinx_dropdown_toggle-1.3.3.dist-info/licenses/LICENSE
sphinx_dropdown_toggle-1.3.3.dist-info/RECORD
