Metadata-Version: 2.4
Name: sphinx-dropdown-toggle
Version: 1.3.3
Summary: Sphinx extension that, on pages with dropdown elements, adds a button to open/close all dropdowns simultaneously.
Author-email: Dennis den Ouden-van der Horst <d.denouden-vanderhorst@tudelft.nl>, Tom van Woudenberg <T.R.vanWoudenberg@tudelft.nl>
License-File: LICENSE
Requires-Python: >=3.10
Requires-Dist: jupyterbook-patches>=1.13.1
Requires-Dist: sphinx
